Workbook

Sheet Summary
A1: OneRoot Essentials Operations Register
A2: Capture expenses, daily sales, apartments, and petty cash without using business-unit columns.
A4: Metric | B4: Value | D4: OneRoot business areas covered
A5: Total Expenses | B5: =SUM(Expenses!H2:H300) -> 4174 | D5: OneRoot Water & Equipment Rentals
A6: Expense Budgeted | B6: =SUM(Budget_Planner!D2:D300) -> 0 | D6: OneRoot Cold Store & Groceries
A7: Total Daily Sales | B7: =SUM(Daily_Sales!C2:C300) -> 3300.3 | D7: OneRoot Laundry Services
A8: Net Sales Less Expenses | B8: =B7-B5 -> -873.7 | D8: OneRoot Mobile Money Services
A9: Rent Due | B9: =SUM(Apartments!M2:M300) -> 0 | D9: OneRoot Rentals & Apartments
A10: Rent Paid | B10: =SUM(Apartments!N2:N300) -> 0 | D10: OneRoot Fresh Foods & Drinks
A11: Bills Paid | B11: =SUM(Apartments!AA2:AA300) -> 0 | D11: OneRoot Kitchen
A12: Petty Cash Budgeted | B12: =SUM(Petty_Cash_Budget!C2:C300) -> 0 | D12: OneRoot Shared Operations
A13: Petty Cash Expense Paid | B13: =SUMIF(Petty_Cash!B2:B300,"Expense Paid",Petty_Cash!G2:G300) -> 421
A14: Petty Cash Balance | B14: =SUM(Petty_Cash!H2:H300) -> 890.7
A15: Petty Cash Budget Remaining | B15: =B12-B13 -> -421
A16: Workbook workflow: fill Expenses, Budget_Planner, Daily_Sales, Apartments, Petty_Cash, and Petty_Cash_Budget. Dropdown columns are preloaded from Lists.
A17: Apartment bills captured: water bill, toilet bill, sweeping and gutter cleaning bill, and waste management bill.
A19: Petty cash ledger captures opening float, top-ups, expense-paid entries, cash returns, adjustments, and monthly budgets.

Sheet Expenses
A1: Date | B1: Business Area | C1: Vendor / Payee | D1: Expense Type | E1: Description | F1: Payment Method | G1: Receipt Status | H1: Amount (GHS) | I1: Notes
A2: 46174 | B2: OneRoot Cold Store & Groceries | C2: Daniel Lamadeku | D2: Inventory Purchase | F2: Mobile Money | G2: Not Required | H2: 800
A3: 46200 | B3: OneRoot Cold Store & Groceries | D3: Inventory Purchase | F3: Cash | G3: Not Required | H3: 611
A4: 46200 | B4: OneRoot Kitchen | D4: Inventory Purchase | F4: Cash | G4: Not Required | H4: 2578
A5: 46200 | B5: OneRoot Kitchen | D5: Fuel & Delivery | F5: Cash | G5: Not Required | H5: 100
A6: 46201 | B6: OneRoot Kitchen | D6: Fuel & Delivery | F6: Cash | G6: Not Required | H6: 50
A7: 46201 | B7: OneRoot Kitchen | D7: Other / Custom | F7: Cash | G7: Not Required | H7: 30
A8: 46201 | B8: OneRoot Kitchen | D8: Fuel & Delivery | F8: Cash | G8: Not Required | H8: 5

Sheet Budget_Planner
A1: Budget Month | B1: Business Area | C1: Expense Type | D1: Budget Amount (GHS) | E1: Actual Spend (GHS) | F1: Variance (GHS) | G1: Notes
E2: =SUMIFS(Expenses!$H$2:$H$300,Expenses!$B$2:$B$300,B2,Expenses!$D$2:$D$300,C2,Expenses!$A$2:$A$300,">="&EOMONTH(A2,-1)+1,Expenses!$A$2:$A$300,"<="&EOMONTH(A2,0)) -> 0 | F2: =D2-E2 -> 0
E3: =SUMIFS(Expenses!$H$2:$H$300,Expenses!$B$2:$B$300,B3,Expenses!$D$2:$D$300,C3,Expenses!$A$2:$A$300,">="&EOMONTH(A3,-1)+1,Expenses!$A$2:$A$300,"<="&EOMONTH(A3,0)) -> 0 | F3: =D3-E3 -> 0
E4: =SUMIFS(Expenses!$H$2:$H$300,Expenses!$B$2:$B$300,B4,Expenses!$D$2:$D$300,C4,Expenses!$A$2:$A$300,">="&EOMONTH(A4,-1)+1,Expenses!$A$2:$A$300,"<="&EOMONTH(A4,0)) -> 0 | F4: =D4-E4 -> 0
E5: =SUMIFS(Expenses!$H$2:$H$300,Expenses!$B$2:$B$300,B5,Expenses!$D$2:$D$300,C5,Expenses!$A$2:$A$300,">="&EOMONTH(A5,-1)+1,Expenses!$A$2:$A$300,"<="&EOMONTH(A5,0)) -> 0 | F5: =D5-E5 -> 0
E6: =SUMIFS(Expenses!$H$2:$H$300,Expenses!$B$2:$B$300,B6,Expenses!$D$2:$D$300,C6,Expenses!$A$2:$A$300,">="&EOMONTH(A6,-1)+1,Expenses!$A$2:$A$300,"<="&EOMONTH(A6,0)) -> 0 | F6: =D6-E6 -> 0
E7: =SUMIFS(Expenses!$H$2:$H$300,Expenses!$B$2:$B$300,B7,Expenses!$D$2:$D$300,C7,Expenses!$A$2:$A$300,">="&EOMONTH(A7,-1)+1,Expenses!$A$2:$A$300,"<="&EOMONTH(A7,0)) -> 0 | F7: =D7-E7 -> 0
E8: =SUMIFS(Expenses!$H$2:$H$300,Expenses!$B$2:$B$300,B8,Expenses!$D$2:$D$300,C8,Expenses!$A$2:$A$300,">="&EOMONTH(A8,-1)+1,Expenses!$A$2:$A$300,"<="&EOMONTH(A8,0)) -> 0 | F8: =D8-E8 -> 0
E9: =SUMIFS(Expenses!$H$2:$H$300,Expenses!$B$2:$B$300,B9,Expenses!$D$2:$D$300,C9,Expenses!$A$2:$A$300,">="&EOMONTH(A9,-1)+1,Expenses!$A$2:$A$300,"<="&EOMONTH(A9,0)) -> 0 | F9: =D9-E9 -> 0
E10: =SUMIFS(Expenses!$H$2:$H$300,Expenses!$B$2:$B$300,B10,Expenses!$D$2:$D$300,C10,Expenses!$A$2:$A$300,">="&EOMONTH(A10,-1)+1,Expenses!$A$2:$A$300,"<="&EOMONTH(A10,0)) -> 0 | F10: =D10-E10 -> 0
E11: =SUMIFS(Expenses!$H$2:$H$300,Expenses!$B$2:$B$300,B11,Expenses!$D$2:$D$300,C11,Expenses!$A$2:$A$300,">="&EOMONTH(A11,-1)+1,Expenses!$A$2:$A$300,"<="&EOMONTH(A11,0)) -> 0 | F11: =D11-E11 -> 0
E12: =SUMIFS(Expenses!$H$2:$H$300,Expenses!$B$2:$B$300,B12,Expenses!$D$2:$D$300,C12,Expenses!$A$2:$A$300,">="&EOMONTH(A12,-1)+1,Expenses!$A$2:$A$300,"<="&EOMONTH(A12,0)) -> 0 | F12: =D12-E12 -> 0
E13: =SUMIFS(Expenses!$H$2:$H$300,Expenses!$B$2:$B$300,B13,Expenses!$D$2:$D$300,C13,Expenses!$A$2:$A$300,">="&EOMONTH(A13,-1)+1,Expenses!$A$2:$A$300,"<="&EOMONTH(A13,0)) -> 0 | F13: =D13-E13 -> 0
... E300: =SUMIFS(Expenses!$H$2:$H$300,Expenses!$B$2:$B$300,B300,Expenses!$D$2:$D$300,C300,Expenses!$A$2:$A$300,">="&EOMONTH(A300,-1)+1,Expenses!$A$2:$A$300,"<="&EOMONTH(A300,0)) -> 0 | F300: =D300-E300 -> 0

Sheet Daily_Sales
A1: Date | B1: Business Area | C1: Total Daily Sales (GHS) | D1: Notes
A2: 46198 | B2: OneRoot Cold Store & Groceries | C2: 366.5
A3: 46198 | B3: OneRoot Kitchen | C3: 98
A4: 46197 | B4: OneRoot Cold Store & Groceries | C4: 298.5
A5: 46197 | B5: OneRoot Kitchen | C5: 105
A6: 46196 | B6: OneRoot Cold Store & Groceries | C6: 239.5
A7: 46196 | B7: OneRoot Kitchen | C7: 145.1
A8: 46195 | B8: OneRoot Kitchen | C8: 307
A9: 46195 | B9: OneRoot Cold Store & Groceries | C9: 314
A10: 46199 | B10: OneRoot Cold Store & Groceries | C10: 435.5
A11: 46199 | B11: OneRoot Kitchen | C11: 221
A12: 46200 | B12: OneRoot Cold Store & Groceries | C12: 550.2
A13: 46200 | B13: OneRoot Kitchen | C13: 220

Sheet Apartments
A1: Billing Month | B1: Suite | C1: Status | D1: Tenant | E1: Tenant Phone | F1: Emergency Contact | G1: ID Ref | H1: Move-In | I1: Move-Out | J1: Rent Cycle | K1: Cycle Months | L1: Cycle Amount (GHS) | M1: Rent Due (GHS) | N1: Rent Paid (GHS) | O1: Coverage Start | P1: Coverage End | Q1: Next Rent Due | R1: Renewal Date | S1: Rent Payment Date | T1: Rent Payment Method | U1: Rent Reference | V1: Water Bill (GHS) | W1: Toilet Bill (GHS) | X1: Sweeping Bill (GHS) | Y1: Waste Bill (GHS) | Z1: Bill Due Date | AA1: Bills Paid (GHS) | AB1: Bill Payment Date | AC1: Bill Payment Method | AD1: Bill Reference | AE1: Arrears B/F (GHS) | AF1: Late Fee (GHS) | AG1: Custom Total (GHS) | AH1: Custom Bill Items | AI1: Notes | AJ1: Total Bills Due (GHS) | AK1: Total Balance Due (GHS)
AJ2: =SUM(V2:Y2)+AG2 -> 0 | AK2: =MAX(M2-N2,0)+MAX(AJ2-AA2,0)+AE2+AF2 -> 0
AJ3: =SUM(V3:Y3)+AG3 -> 0 | AK3: =MAX(M3-N3,0)+MAX(AJ3-AA3,0)+AE3+AF3 -> 0
AJ4: =SUM(V4:Y4)+AG4 -> 0 | AK4: =MAX(M4-N4,0)+MAX(AJ4-AA4,0)+AE4+AF4 -> 0
AJ5: =SUM(V5:Y5)+AG5 -> 0 | AK5: =MAX(M5-N5,0)+MAX(AJ5-AA5,0)+AE5+AF5 -> 0
AJ6: =SUM(V6:Y6)+AG6 -> 0 | AK6: =MAX(M6-N6,0)+MAX(AJ6-AA6,0)+AE6+AF6 -> 0
AJ7: =SUM(V7:Y7)+AG7 -> 0 | AK7: =MAX(M7-N7,0)+MAX(AJ7-AA7,0)+AE7+AF7 -> 0
AJ8: =SUM(V8:Y8)+AG8 -> 0 | AK8: =MAX(M8-N8,0)+MAX(AJ8-AA8,0)+AE8+AF8 -> 0
AJ9: =SUM(V9:Y9)+AG9 -> 0 | AK9: =MAX(M9-N9,0)+MAX(AJ9-AA9,0)+AE9+AF9 -> 0
AJ10: =SUM(V10:Y10)+AG10 -> 0 | AK10: =MAX(M10-N10,0)+MAX(AJ10-AA10,0)+AE10+AF10 -> 0
AJ11: =SUM(V11:Y11)+AG11 -> 0 | AK11: =MAX(M11-N11,0)+MAX(AJ11-AA11,0)+AE11+AF11 -> 0
AJ12: =SUM(V12:Y12)+AG12 -> 0 | AK12: =MAX(M12-N12,0)+MAX(AJ12-AA12,0)+AE12+AF12 -> 0
AJ13: =SUM(V13:Y13)+AG13 -> 0 | AK13: =MAX(M13-N13,0)+MAX(AJ13-AA13,0)+AE13+AF13 -> 0
... AJ300: =SUM(V300:Y300)+AG300 -> 0 | AK300: =MAX(M300-N300,0)+MAX(AJ300-AA300,0)+AE300+AF300 -> 0

Sheet Petty_Cash
A1: Date | B1: Transaction Type | C1: Business Area | D1: Expense Type | E1: Payee / Purpose | F1: Receipt Status | G1: Amount (GHS) | H1: Cash Effect (GHS) | I1: Notes
A2: 46174 | B2: Opening Float | C2: OneRoot Kitchen | D2: Inventory Purchase | E2: Erica Asare | F2: Not Required | G2: 500 | H2: =IF(OR(B2="Opening Float",B2="Cash Top-up",B2="Adjustment In"),G2,IF(OR(B2="Expense Paid",B2="Cash Returned",B2="Adjustment Out"),-G2,0)) -> 500
A3: 46175 | B3: Opening Float | C3: OneRoot Cold Store & Groceries | D3: Inventory Purchase | E3: Emmanuella Asare | F3: Not Required | G3: 500 | H3: =IF(OR(B3="Opening Float",B3="Cash Top-up",B3="Adjustment In"),G3,IF(OR(B3="Expense Paid",B3="Cash Returned",B3="Adjustment Out"),-G3,0)) -> 500
A4: 46196 | B4: Expense Paid | C4: OneRoot Kitchen | D4: Inventory Purchase | E4: Erica Asare | F4: Not Required | G4: 15 | H4: =IF(OR(B4="Opening Float",B4="Cash Top-up",B4="Adjustment In"),G4,IF(OR(B4="Expense Paid",B4="Cash Returned",B4="Adjustment Out"),-G4,0)) -> -15
A5: 46196 | B5: Expense Paid | C5: OneRoot Kitchen | D5: Inventory Purchase | E5: Erica Asare | F5: Not Required | G5: 210 | H5: =IF(OR(B5="Opening Float",B5="Cash Top-up",B5="Adjustment In"),G5,IF(OR(B5="Expense Paid",B5="Cash Returned",B5="Adjustment Out"),-G5,0)) -> -210
A6: 46196 | B6: Expense Paid | C6: OneRoot Kitchen | D6: Inventory Purchase | E6: Erica Asare | F6: Not Required | G6: 17 | H6: =IF(OR(B6="Opening Float",B6="Cash Top-up",B6="Adjustment In"),G6,IF(OR(B6="Expense Paid",B6="Cash Returned",B6="Adjustment Out"),-G6,0)) -> -17
A7: 46196 | B7: Expense Paid | C7: OneRoot Kitchen | D7: Inventory Purchase | E7: Erica Asare | F7: Not Required | G7: 85 | H7: =IF(OR(B7="Opening Float",B7="Cash Top-up",B7="Adjustment In"),G7,IF(OR(B7="Expense Paid",B7="Cash Returned",B7="Adjustment Out"),-G7,0)) -> -85
A8: 46196 | B8: Expense Paid | C8: OneRoot Kitchen | D8: Inventory Purchase | E8: Erica Asare | F8: Not Required | G8: 50 | H8: =IF(OR(B8="Opening Float",B8="Cash Top-up",B8="Adjustment In"),G8,IF(OR(B8="Expense Paid",B8="Cash Returned",B8="Adjustment Out"),-G8,0)) -> -50
A9: 46199 | B9: Expense Paid | C9: OneRoot Cold Store & Groceries | D9: Inventory Purchase | E9: Emmanuella Asare | F9: Not Required | G9: 44 | H9: =IF(OR(B9="Opening Float",B9="Cash Top-up",B9="Adjustment In"),G9,IF(OR(B9="Expense Paid",B9="Cash Returned",B9="Adjustment Out"),-G9,0)) -> -44
A10: 46200 | B10: Opening Float | C10: OneRoot Cold Store & Groceries | D10: Other / Custom | E10: Emmanuella Asare | F10: Not Required | G10: 311.7 | H10: =IF(OR(B10="Opening Float",B10="Cash Top-up",B10="Adjustment In"),G10,IF(OR(B10="Expense Paid",B10="Cash Returned",B10="Adjustment Out"),-G10,0)) -> 311.7
H11: =IF(OR(B11="Opening Float",B11="Cash Top-up",B11="Adjustment In"),G11,IF(OR(B11="Expense Paid",B11="Cash Returned",B11="Adjustment Out"),-G11,0)) -> 0
H12: =IF(OR(B12="Opening Float",B12="Cash Top-up",B12="Adjustment In"),G12,IF(OR(B12="Expense Paid",B12="Cash Returned",B12="Adjustment Out"),-G12,0)) -> 0
H13: =IF(OR(B13="Opening Float",B13="Cash Top-up",B13="Adjustment In"),G13,IF(OR(B13="Expense Paid",B13="Cash Returned",B13="Adjustment Out"),-G13,0)) -> 0
H14: =IF(OR(B14="Opening Float",B14="Cash Top-up",B14="Adjustment In"),G14,IF(OR(B14="Expense Paid",B14="Cash Returned",B14="Adjustment Out"),-G14,0)) -> 0
H15: =IF(OR(B15="Opening Float",B15="Cash Top-up",B15="Adjustment In"),G15,IF(OR(B15="Expense Paid",B15="Cash Returned",B15="Adjustment Out"),-G15,0)) -> 0
H16: =IF(OR(B16="Opening Float",B16="Cash Top-up",B16="Adjustment In"),G16,IF(OR(B16="Expense Paid",B16="Cash Returned",B16="Adjustment Out"),-G16,0)) -> 0
H17: =IF(OR(B17="Opening Float",B17="Cash Top-up",B17="Adjustment In"),G17,IF(OR(B17="Expense Paid",B17="Cash Returned",B17="Adjustment Out"),-G17,0)) -> 0
H18: =IF(OR(B18="Opening Float",B18="Cash Top-up",B18="Adjustment In"),G18,IF(OR(B18="Expense Paid",B18="Cash Returned",B18="Adjustment Out"),-G18,0)) -> 0
H19: =IF(OR(B19="Opening Float",B19="Cash Top-up",B19="Adjustment In"),G19,IF(OR(B19="Expense Paid",B19="Cash Returned",B19="Adjustment Out"),-G19,0)) -> 0
H20: =IF(OR(B20="Opening Float",B20="Cash Top-up",B20="Adjustment In"),G20,IF(OR(B20="Expense Paid",B20="Cash Returned",B20="Adjustment Out"),-G20,0)) -> 0
H21: =IF(OR(B21="Opening Float",B21="Cash Top-up",B21="Adjustment In"),G21,IF(OR(B21="Expense Paid",B21="Cash Returned",B21="Adjustment Out"),-G21,0)) -> 0
H22: =IF(OR(B22="Opening Float",B22="Cash Top-up",B22="Adjustment In"),G22,IF(OR(B22="Expense Paid",B22="Cash Returned",B22="Adjustment Out"),-G22,0)) -> 0
... H300: =IF(OR(B300="Opening Float",B300="Cash Top-up",B300="Adjustment In"),G300,IF(OR(B300="Expense Paid",B300="Cash Returned",B300="Adjustment Out"),-G300,0)) -> 0

Sheet Petty_Cash_Budget
A1: Budget Month | B1: Business Area | C1: Budget Amount (GHS) | D1: Notes

Sheet Lists
A1: Business Areas | B1: Expense Types | C1: Payment Methods | D1: Receipt Statuses | E1: Suites | F1: Petty Cash Types | G1: Occupancy Statuses | H1: Rent Cycles
A2: OneRoot Water & Equipment Rentals | B2: Water Stock & Supply | C2: Bank Transfer | D2: Uploaded | E2: Peace Suite | F2: Opening Float | G2: Occupied | H2: 6 Months
A3: OneRoot Cold Store & Groceries | B3: Equipment Repairs | C3: Cash | D3: Pending | E3: Grace Suite | F3: Cash Top-up | G3: Vacant | H3: 12 Months
A4: OneRoot Laundry Services | B4: Fuel & Delivery | C4: Card | D4: Not Required | E4: Joy Suite | F4: Expense Paid | G4: Reserved | H4: Custom
A5: OneRoot Mobile Money Services | B5: Tools & Consumables | C5: Mobile Money | E5: Hope Suite | F5: Cash Returned | G5: Under Maintenance
A6: OneRoot Rentals & Apartments | B6: Site Labour | C6: Cheque | E6: Faith Suite | F6: Adjustment In
A7: OneRoot Fresh Foods & Drinks | B7: Utilities | C7: Petty Cash | E7: Love Suite | F7: Adjustment Out
A8: OneRoot Kitchen | B8: Marketing & Promotion | E8: Wisdom Suite
A9: OneRoot Shared Operations | B9: Professional Services | E9: Unity Suite
B10: Rent & Space | E10: Harmony Suite
B11: Inventory Purchase | E11: Additional Suites / Common Areas
B12: Cold Chain Utilities | E12: Other / Custom
B13: Packaging & Carrier Bags
B14: Delivery & Transport
B15: Spoilage & Waste
B16: Repairs & Maintenance
B17: Staff Wages
B18: Detergents & Laundry Supplies
B19: Machine Repairs
B20: Power & Water
B21: Packaging & Hangers
B22: Transaction Charges
B23: Booth Utilities
B24: Cash Handling & Security
... B46: Other / Custom
